capella2polarion/__init__.py
capella2polarion/__main__.py
capella2polarion/cli.py
capella2polarion/polarion_html_helper.py
capella2polarion/py.typed
capella2polarion/connectors/__init__.py
capella2polarion/connectors/polarion_repo.py
capella2polarion/connectors/polarion_worker.py
capella2polarion/data_model/__init__.py
capella2polarion/data_model/document_data.py
capella2polarion/data_model/work_item_attachments.py
capella2polarion/data_model/work_items.py
capella2polarion/documents/__init__.py
capella2polarion/documents/document_config.py
capella2polarion/documents/document_renderer.py
capella2polarion/documents/mass_document_renderer.py
capella2polarion/documents/text_work_item_provider.py
capella2polarion/elements/__init__.py
capella2polarion/elements/capella_object_renderer.py
capella2polarion/elements/converter_config.py
capella2polarion/elements/data_session.py
capella2polarion/elements/element_converter.py
capella2polarion/elements/link_converter.py
capella2polarion/elements/model_converter.py
capella2polarion/plugins/__init__.py
capella2polarion/plugins/plugin_config.py
capella2polarion/plugins/plugin_interfaces.py
capella2polarion-1.6.4.dist-info/licenses/LICENSES/Apache-2.0.txt
capella2polarion-1.6.4.dist-info/licenses/LICENSES/CC0-1.0.txt
capella2polarion-1.6.4.dist-info/METADATA
capella2polarion-1.6.4.dist-info/WHEEL
capella2polarion-1.6.4.dist-info/entry_points.txt
capella2polarion-1.6.4.dist-info/top_level.txt
capella2polarion-1.6.4.dist-info/RECORD
