Metadata-Version: 2.4
Name: capella2polarion
Version: 1.6.4
Summary: Synchronise Capella models with Polarion projects
Author: DB InfraGO AG
License-Expression: Apache-2.0
Project-URL: Homepage, https://github.com/dbinfrago/capella-polarion
Project-URL: Documentation, https://dbinfrago.github.io/capella-polarion
Platform: any
Classifier: Development Status :: 1 - Planning
Classifier: Natural Language :: English
Classifier: Operating System :: OS Independent
Classifier: Programming Language :: Python :: 3 :: Only
Classifier: Programming Language :: Python :: 3.10
Classifier: Programming Language :: Python :: 3.11
Classifier: Programming Language :: Python :: 3.12
Classifier: Programming Language :: Python :: 3.13
Classifier: Typing :: Typed
Requires-Python: <3.14,>=3.10
License-File: LICENSES/Apache-2.0.txt
License-File: LICENSES/CC0-1.0.txt
Requires-Dist: bidict
Requires-Dist: cairosvg
Requires-Dist: capellambse<0.8,>=0.7.2
Requires-Dist: capellambse_context_diagrams<0.8,>=0.7.0
Requires-Dist: click
Requires-Dist: python-datauri<4,>=3.0.2
Requires-Dist: jinja2
Requires-Dist: polarion-rest-api-client<1.5,>=1.4.4
Requires-Dist: pydantic
Requires-Dist: pyyaml
Dynamic: license-file
